MANIFEST.in
README.md
README.zh-CN.md
requirements.txt
setup.py
keras_pos_embd/__init__.py
keras_pos_embd/pos_embd.py
keras_pos_embd/trig_pos_embd.py
keras_pos_embd.egg-info/PKG-INFO
keras_pos_embd.egg-info/SOURCES.txt
keras_pos_embd.egg-info/dependency_links.txt
keras_pos_embd.egg-info/requires.txt
keras_pos_embd.egg-info/top_level.txt
tests/__init__.py
tests/test_pos_embd.py
tests/test_trig_pos_embd.py