Metadata-Version: 2.1
Name: keras-pos-embd
Version: 0.13.0
Summary: Position embedding layers in Keras
Home-page: https://github.com/CyberZHG/keras-pos-embd
Author: CyberZHG
Author-email: CyberZHG@users.noreply.github.com
License: MIT
Platform: UNKNOWN
Classifier: Programming Language :: Python :: 3
Classifier: License :: OSI Approved :: MIT License
Classifier: Operating System :: OS Independent
